dpj/__init__.py
dpj/__main__.py
dpj/cli.py
dpj/utils.py
dpj-3.6.0.dist-info/licenses/LICENSE
dpj-3.6.0.dist-info/METADATA
dpj-3.6.0.dist-info/WHEEL
dpj-3.6.0.dist-info/entry_points.txt
dpj-3.6.0.dist-info/top_level.txt
dpj-3.6.0.dist-info/RECORD
