Metadata-Version: 2.4
Name: dpj
Version: 3.6.0
Summary: A simple CLI tool for encrypting/hashing files and strings.
Home-page: https://github.com/jheffat/DPJ
Author: Jheff MAT
Author-email: Jheff AT <jheff.at@gmail.com>
License: MIT License
Requires-Python: >=3.6
License-File: LICENSE
Requires-Dist: prompt_toolkit
Requires-Dist: argparse
Dynamic: author
Dynamic: home-page
Dynamic: license-file
Dynamic: requires-python
